ally_ai_langsmith/Langsmith.py
ally_ai_langsmith/__init__.py
ally_ai_langsmith-0.0.1.dist-info/LICENSE
ally_ai_langsmith-0.0.1.dist-info/METADATA
ally_ai_langsmith-0.0.1.dist-info/WHEEL
ally_ai_langsmith-0.0.1.dist-info/top_level.txt
ally_ai_langsmith-0.0.1.dist-info/RECORD
